{
	"results":{
	    "enterpriseList":[
	    		{"id":0,"number":"00","category":"021122","name":"上海冕冠","tel":"13162875213","legal_person":"卡卡","principal":"来啦","biz_scope":"包括很多、很多、、、","province":"上海虹口区","city":"虹口区","address":"上海虹口江湾镇","release_date":"2015-07-07","due_date":"2030-7-7"},
				{"id":1,"number":"11","category":"3243","name":"上海冕冠","tel":"13162875213","legal_person":"卡卡","principal":"来啦","biz_scope":"包括很多、很多、、、","province":"上海虹口区","city":"虹口区","address":"上海虹口江湾镇","release_date":"2015-07-07","due_date":"2030-7-7"}
	   		 ]
	   	},
	"msg":"success",
	"code":200
}